compliant_social_django/__init__.py
compliant_social_django/admin.py
compliant_social_django/apps.py
compliant_social_django/config.py
compliant_social_django/context_processors.py
compliant_social_django/decorators.py
compliant_social_django/fields.py
compliant_social_django/managers.py
compliant_social_django/middleware.py
compliant_social_django/models.py
compliant_social_django/models_utils.py
compliant_social_django/storage.py
compliant_social_django/strategy.py
compliant_social_django/urls.py
compliant_social_django/utils.py
compliant_social_django/views.py
compliant_social_django/audit/__init__.py
compliant_social_django/audit/clients.py
compliant_social_django/backends/__init__.py
compliant_social_django/backends/compliant_facebook.py
compliant_social_django/backends/compliant_google.py
compliant_social_django/management/__init__.py
compliant_social_django/management/commands/__init__.py
compliant_social_django/management/commands/clearsocial.py
compliant_social_django/migrations/0001_initial.py
compliant_social_django/migrations/0002_add_related_name.py
compliant_social_django/migrations/0003_alter_email_max_length.py
compliant_social_django/migrations/0004_auto_20160423_0400.py
compliant_social_django/migrations/0005_auto_20160727_2333.py
compliant_social_django/migrations/0006_partial.py
compliant_social_django/migrations/0007_code_timestamp.py
compliant_social_django/migrations/0008_partial_timestamp.py
compliant_social_django/migrations/0009_auto_20191118_0520.py
compliant_social_django/migrations/0010_uid_db_index.py
compliant_social_django/migrations/0011_create_kms_token_fields.py
compliant_social_django/migrations/0012_encrypt_tokens.py
compliant_social_django/migrations/0013_usersocialauth_revoked.py
compliant_social_django/migrations/0014_alter_id_fields.py
compliant_social_django/migrations/0015_usersocialauth_extra_data_new.py
compliant_social_django/migrations/0016_migrate_extra_data.py
compliant_social_app_django-5.4.1.dist-info/LICENSE
compliant_social_app_django-5.4.1.dist-info/METADATA
compliant_social_app_django-5.4.1.dist-info/WHEEL
compliant_social_app_django-5.4.1.dist-info/top_level.txt
compliant_social_app_django-5.4.1.dist-info/RECORD
