Metadata-Version: 2.1
Name: compliant-social-app-django
Version: 5.4.1
Summary: Python Social Authentication, Django integration, Google compliant fork
Home-page: https://github.com/RightlyGroup/compliant-social-app-django
Author: Rightly
Author-email: 
License: BSD
Keywords: django,social auth
Classifier: Development Status :: 5 - Production/Stable
Classifier: Topic :: Internet
Classifier: License :: OSI Approved :: BSD License
Classifier: Intended Audience :: Developers
Classifier: Environment :: Web Environment
Classifier: Programming Language :: Python
Classifier: Programming Language :: Python :: 3
Classifier: Programming Language :: Python :: 3.8
Classifier: Programming Language :: Python :: 3.9
Classifier: Programming Language :: Python :: 3.10
Classifier: Programming Language :: Python :: 3.11
Classifier: Programming Language :: Python :: 3.12
Requires-Python: >=3.8
License-File: LICENSE
Requires-Dist: social-auth-core >=4.4.1
Requires-Dist: django-kms-field ==0.6
Requires-Dist: Django >=3.2
